{"strategy":{"deadzone":{"trades":[{"pair":"BTC/USDT","stake_amount":976.864,"amount":0.049,"open_date":"2022-09-09 04:00:00+00:00","close_date":"2022-09-09 05:30:00+00:00","open_rate":19936.0,"close_rate":20529.0,"fee_open":0.0002,"fee_close":0.0002,"trade_duration":90,"profit_ratio":0.02933336887999607,"profit_abs":28.660443,"exit_reason":"long_TP_hit_20467.072122247024","initial_stop_loss_abs":19688.9,"initial_stop_loss_ratio":-1.0,"stop_loss_abs":19688.9,"stop_loss_ratio":-0.02626482436842037,"min_rate":19916.5,"max_rate":20737.9,"is_open":false,"enter_tag":null,"is_short":false,"open_timestamp":1662696000000,"close_timestamp":1662701400000,"orders":[{"amount":0.049,"safe_price":19936.0,"ft_order_side":"buy","order_filled_timestamp":1662696000000,"ft_is_entry":true},{"amount":0.049,"safe_price":20529.0,"ft_order_side":"sell","order_filled_timestamp":1662701400000,"ft_is_entry":false}]},{"pair":"BTC/USDT","stake_amount":1005.9847,"amount":0.049,"open_date":"2022-09-09 05:45:00+00:00","close_date":"2022-09-09 10:30:00+00:00","open_rate":20530.3,"close_rate":20855.7,"fee_open":0.0002,"fee_close":0.0002,"trade_duration":285,"profit_ratio":0.015343051027598116,"profit_abs":15.43796156,"exit_reason":"long_TP_hit_20811.94427347319","initial_stop_loss_abs":20244.7,"initial_stop_loss_ratio":-1.0,"stop_loss_abs":20244.7,"stop_loss_ratio":-0.01372594675506622,"min_rate":20472.4,"max_rate":21125.0,"is_open":false,"enter_tag":null,"is_short":false,"open_timestamp":1662702300000,"close_timestamp":1662719400000,"orders":[{"amount":0.049,"safe_price":20530.3,"ft_order_side":"buy","order_filled_timestamp":1662702300000,"ft_is_entry":true},{"amount":0.049,"safe_price":20855.7,"ft_order_side":"sell","order_filled_timestamp":1662719400000,"ft_is_entry":false}]},{"pair":"BTC/USDT","stake_amount":1026.0535,"amount":0.053,"open_date":"2022-09-23 23:15:00+00:00","close_date":"2022-09-24 00:15:00+00:00","open_rate":19359.5,"close_rate":19138.5,"fee_open":0.0002,"fee_close":0.0002,"trade_duration":60,"profit_ratio":-0.011840282955271389,"profit_abs":-12.15119352,"exit_reason":"stop_loss","initial_stop_loss_abs":19138.5,"initial_stop_loss_ratio":-1.0,"stop_loss_abs":19138.5,"stop_loss_ratio":-0.010396443193648852,"min_rate":19135.6,"max_rate":19398.0,"is_open":false,"enter_tag":null,"is_short":false,"open_timestamp":1663974900000,"close_timestamp":1663978500000,"orders":[{"amount":0.053,"safe_price":19359.5,"ft_order_side":"buy","order_filled_timestamp":1663974900000,"ft_is_entry":true},{"amount":0.053,"safe_price":19138.5,"ft_order_side":"sell","order_filled_timestamp":1663978500000,"ft_is_entry":false}]},{"pair":"BTC/USDT","stake_amount":1005.0,"amount":0.05,"open_date":"2022-09-30 15:15:00+00:00","close_date":"2022-09-30 15:45:00+00:00","open_rate":20100.0,"close_rate":19829.7,"fee_open":0.0002,"fee_close":0.0002,"trade_duration":30,"profit_ratio":-0.013842303181154814,"profit_abs":-13.914297,"exit_reason":"stop_loss","initial_stop_loss_abs":19829.7,"initial_stop_loss_ratio":-1.0,"stop_loss_abs":19829.7,"stop_loss_ratio":-0.009793492893180322,"min_rate":19674.8,"max_rate":20150.0,"is_open":false,"enter_tag":null,"is_short":false,"open_timestamp":1664550900000,"close_timestamp":1664552700000,"orders":[{"amount":0.05,"safe_price":20100.0,"ft_order_side":"buy","order_filled_timestamp":1664550900000,"ft_is_entry":true},{"amount":0.05,"safe_price":19829.7,"ft_order_side":"sell","order_filled_timestamp":1664552700000,"ft_is_entry":false}]},{"pair":"BTC/USDT","stake_amount":1007.2245,"amount":0.051,"open_date":"2022-09-30 16:00:00+00:00","close_date":"2022-09-30 20:00:00+00:00","open_rate":19749.5,"close_rate":19442.3,"fee_open":0.0002,"fee_close":0.0002,"trade_duration":240,"profit_ratio":-0.01604850350722787,"profit_abs":-16.16767881,"exit_reason":"stop_loss","initial_stop_loss_abs":19442.3,"initial_stop_loss_ratio":-1.0,"stop_loss_abs":19442.3,"stop_loss_ratio":-0.011306860925923923,"min_rate":19343.0,"max_rate":19865.2,"is_open":false,"enter_tag":null,"is_short":false,"open_timestamp":1664553600000,"close_timestamp":1664568000000,"orders":[{"amount":0.051,"safe_price":19749.5,"ft_order_side":"buy","order_filled_timestamp":1664553600000,"ft_is_entry":true},{"amount":0.051,"safe_price":19442.3,"ft_order_side":"sell","order_filled_timestamp":1664568000000,"ft_is_entry":false}]}],"locks":[],"best_pair":{"key":"BTC/USDT","trades":5,"profit_mean":0.0005890660527880232,"profit_mean_pct":0.058906605278802315,"profit_sum":0.0029453302639401158,"profit_sum_pct":0.29,"profit_total_abs":1.8652352299999997,"profit_total":0.0018652352299999998,"profit_total_pct":0.19,"duration_avg":"2:21:00","wins":2,"draws":0,"losses":3},"worst_pair":{"key":"BTC/USDT","trades":5,"profit_mean":0.0005890660527880232,"profit_mean_pct":0.058906605278802315,"profit_sum":0.0029453302639401158,"profit_sum_pct":0.29,"profit_total_abs":1.8652352299999997,"profit_total":0.0018652352299999998,"profit_total_pct":0.19,"duration_avg":"2:21:00","wins":2,"draws":0,"losses":3},"results_per_pair":[{"key":"BTC/USDT","trades":5,"profit_mean":0.0005890660527880232,"profit_mean_pct":0.058906605278802315,"profit_sum":0.0029453302639401158,"profit_sum_pct":0.29,"profit_total_abs":1.8652352299999997,"profit_total":0.0018652352299999998,"profit_total_pct":0.19,"duration_avg":"2:21:00","wins":2,"draws":0,"losses":3},{"key":"TOTAL","trades":5,"profit_mean":0.0005890660527880232,"profit_mean_pct":0.058906605278802315,"profit_sum":0.0029453302639401158,"profit_sum_pct":0.29,"profit_total_abs":1.8652352299999997,"profit_total":0.0018652352299999998,"profit_total_pct":0.19,"duration_avg":"2:21:00","wins":2,"draws":0,"losses":3}],"results_per_enter_tag":[{"key":"TOTAL","trades":5,"profit_mean":0.0005890660527880232,"profit_mean_pct":0.058906605278802315,"profit_sum":0.0029453302639401158,"profit_sum_pct":0.29,"profit_total_abs":1.8652352299999997,"profit_total":0.0018652352299999998,"profit_total_pct":0.19,"duration_avg":"2:21:00","wins":2,"draws":0,"losses":3}],"exit_reason_summary":[{"exit_reason":"stop_loss","trades":3,"wins":0,"draws":0,"losses":3,"profit_mean":-0.013910363214551358,"profit_mean_pct":-1.39,"profit_sum":-0.041731089643654073,"profit_sum_pct":-4.17,"profit_total_abs":-42.233169329999996,"profit_total":-0.041731089643654073,"profit_total_pct":-4.17},{"exit_reason":"long_TP_hit_20467.072122247024","trades":1,"wins":1,"draws":0,"losses":0,"profit_mean":0.02933336887999607,"profit_mean_pct":2.93,"profit_sum":0.02933336887999607,"profit_sum_pct":2.93,"profit_total_abs":28.660443,"profit_total":0.02933336887999607,"profit_total_pct":2.93},{"exit_reason":"long_TP_hit_20811.94427347319","trades":1,"wins":1,"draws":0,"losses":0,"profit_mean":0.015343051027598116,"profit_mean_pct":1.53,"profit_sum":0.015343051027598116,"profit_sum_pct":1.53,"profit_total_abs":15.43796156,"profit_total":0.015343051027598116,"profit_total_pct":1.53}],"left_open_trades":[{"key":"TOTAL","trades":0,"profit_mean":0.0,"profit_mean_pct":0.0,"profit_sum":0.0,"profit_sum_pct":0.0,"profit_total_abs":0.0,"profit_total":0.0,"profit_total_pct":0.0,"duration_avg":"0:00","wins":0,"draws":0,"losses":0}],"total_trades":5,"trade_count_long":5,"trade_count_short":0,"total_volume":5021.1267,"avg_stake_amount":1004.22534,"profit_mean":0.0005890660527880232,"profit_median":-0.011840282955271389,"profit_total":0.0018652352299999998,"profit_total_long":0.0018652352299999998,"profit_total_short":0.0,"profit_total_abs":1.8652352299999997,"profit_total_long_abs":1.8652352299999997,"profit_total_short_abs":0.0,"cagr":0.02373158614434745,"profit_factor":1.0441651730047892,"backtest_start":"2022-09-02 00:00:00","backtest_start_ts":1662076800000,"backtest_end":"2022-10-01 22:30:00","backtest_end_ts":1664663400000,"backtest_days":29,"backtest_run_start_ts":1664732072,"backtest_run_end_ts":1664732072,"trades_per_day":0.17,"market_change":-0.017360245444970623,"pairlist":["BTC/USDT"],"stake_amount":"unlimited","stake_currency":"USDT","stake_currency_decimals":3,"starting_balance":1000,"dry_run_wallet":1000,"final_balance":1001.86523523,"rejected_signals":0,"timedout_entry_orders":0,"timedout_exit_orders":0,"canceled_trade_entries":0,"canceled_entry_orders":0,"replaced_entry_orders":0,"max_open_trades":1,"max_open_trades_setting":1,"timeframe":"15m","timeframe_detail":"","timerange":"20220902-","enable_protections":false,"strategy_name":"deadzone","stoploss":-1,"trailing_stop":false,"trailing_stop_positive":null,"trailing_stop_positive_offset":0.0,"trailing_only_offset_is_reached":false,"use_custom_stoploss":true,"minimal_roi":{"60":0.1,"30":1,"0":1},"use_exit_signal":true,"exit_profit_only":false,"exit_profit_offset":0.0,"ignore_roi_if_entry_signal":false,"backtest_best_day":0.04467641990759419,"backtest_worst_day":-0.029890806688382683,"backtest_best_day_abs":44.09840456,"backtest_worst_day_abs":-30.08197581,"winning_days":1,"draw_days":19,"losing_days":2,"daily_profit":[["2022-09-09",44.09840456],["2022-09-10",0.0],["2022-09-11",0.0],["2022-09-12",0.0],["2022-09-13",0.0],["2022-09-14",0.0],["2022-09-15",0.0],["2022-09-16",0.0],["2022-09-17",0.0],["2022-09-18",0.0],["2022-09-19",0.0],["2022-09-20",0.0],["2022-09-21",0.0],["2022-09-22",0.0],["2022-09-23",0.0],["2022-09-24",-12.15119352],["2022-09-25",0.0],["2022-09-26",0.0],["2022-09-27",0.0],["2022-09-28",0.0],["2022-09-29",0.0],["2022-09-30",-30.08197581]],"wins":2,"losses":3,"draws":0,"holding_avg":"2:21:00","holding_avg_s":8460.0,"winner_holding_avg":"3:08:00","winner_holding_avg_s":11280.0,"loser_holding_avg":"1:50:00","loser_holding_avg_s":6600.0,"max_drawdown":0.041731089643654073,"max_drawdown_account":0.040449414677343316,"max_relative_drawdown":0.040449414677343316,"max_drawdown_abs":42.233169329999996,"drawdown_start":"2022-09-09 10:30:00","drawdown_start_ts":1662719400000.0,"drawdown_end":"2022-09-30 20:00:00","drawdown_end_ts":1664568000000.0,"max_drawdown_low":1.8652352299999997,"max_drawdown_high":44.09840456,"csum_min":1001.86523523,"csum_max":1044.09840456}},"strategy_comparison":[{"key":"deadzone","trades":5,"profit_mean":0.0005890660527880232,"profit_mean_pct":0.058906605278802315,"profit_sum":0.0029453302639401158,"profit_sum_pct":0.29,"profit_total_abs":1.8652352299999997,"profit_total":0.0018652352299999998,"profit_total_pct":0.19,"duration_avg":"2:21:00","wins":2,"draws":0,"losses":3,"max_drawdown_account":0.040449414677343316,"max_drawdown_abs":"42.233"}]}